scbl_utils/__init__.py
scbl_utils/main.py
scbl_utils/utils/defaults.py
scbl_utils/utils/gdrive.py
scbl_utils/utils/samplesheet.py
scbl_utils/utils/validate.py
scbl_utils-1.15.dist-info/LICENSE
scbl_utils-1.15.dist-info/METADATA
scbl_utils-1.15.dist-info/WHEEL
scbl_utils-1.15.dist-info/entry_points.txt
scbl_utils-1.15.dist-info/RECORD
