Metadata-Version: 2.1
Name: scbl-utils
Version: 1.15
Summary: A set of command-line utilities that facilitate data processing at the Single Cell Biology Lab at the Jackson Laboratory.
Home-page: https://github.com/TheJacksonLaboratory/scbl-utils/
License: MIT
Author: Ahmed Said
Author-email: ahmed.said@jax.org
Requires-Python: >=3.9,<3.13
Classifier: License :: OSI Approved :: MIT License
Classifier: Programming Language :: Python :: 3
Classifier: Programming Language :: Python :: 3.9
Classifier: Programming Language :: Python :: 3.10
Classifier: Programming Language :: Python :: 3.11
Classifier: Programming Language :: Python :: 3.12
Requires-Dist: PyYAML (>=6.0.1,<7.0.0)
Requires-Dist: google-api-python-client (>=2.108.0,<3.0.0)
Requires-Dist: gspread (>=5.12.0,<6.0.0)
Requires-Dist: jsonschema (>=4.20.0,<5.0.0)
Requires-Dist: pandas[html] (>=2.1.3,<3.0.0)
Requires-Dist: typer[all] (>=0.9.0,<0.10.0)
Project-URL: Documentation, https://github.com/TheJacksonLaboratory/scbl-utils/
Project-URL: Repository, https://github.com/TheJacksonLaboratory/scbl-utils/
